indexer/__init__.py
indexer/index.py
indexer/main.py
indexer/snapshot.py
indexer/util.py
gkeop_snapshot_indexer-1.0.6.dist-info/LICENSE
gkeop_snapshot_indexer-1.0.6.dist-info/METADATA
gkeop_snapshot_indexer-1.0.6.dist-info/WHEEL
gkeop_snapshot_indexer-1.0.6.dist-info/entry_points.txt
gkeop_snapshot_indexer-1.0.6.dist-info/top_level.txt
gkeop_snapshot_indexer-1.0.6.dist-info/RECORD
