Metadata-Version: 2.1
Name: gkeop-snapshot-indexer
Version: 1.0.6
Summary: Simple indexer for a GKE Onprem snapshot bundle
Home-page: https://github.com/dialogbox/gkeop-snapshot-indexer
Author: Jason Kim
Author-email: junchul@google.com
License: MIT
Keywords: gke gkeop gke-onprem
Platform: UNKNOWN
Classifier: Development Status :: 3 - Alpha
Classifier: Intended Audience :: Developers
Classifier: Topic :: System :: Systems Administration
Classifier: License :: OSI Approved :: MIT License
Classifier: Programming Language :: Python
Classifier: Programming Language :: Python :: 3
Classifier: Programming Language :: Python :: 3.6
Classifier: Programming Language :: Python :: 3.7
Classifier: Programming Language :: Python :: 3.8
Requires-Dist: PyYAML (>5)
Requires-Dist: click (>7)
